fixieai/__init__.py
fixieai/agents/__init__.py
fixieai/agents/agent_base.py
fixieai/agents/agent_base_test.py
fixieai/agents/agent_func.py
fixieai/agents/agent_func_test.py
fixieai/agents/api.py
fixieai/agents/api_test.py
fixieai/agents/code_shot.py
fixieai/agents/code_shot_test.py
fixieai/agents/corpora.py
fixieai/agents/corpora_test.py
fixieai/agents/exceptions.py
fixieai/agents/llm_settings.py
fixieai/agents/metadata.py
fixieai/agents/oauth.py
fixieai/agents/openai_proxy.py
fixieai/agents/openai_proxy_test.py
fixieai/agents/standalone.py
fixieai/agents/standalone_test.py
fixieai/agents/token.py
fixieai/agents/user_storage.py
fixieai/agents/user_storage_test.py
fixieai/agents/utils.py
fixieai/agents/utils_test.py
fixieai/cli/__init__.py
fixieai/cli/agent/__init__.py
fixieai/cli/agent/agent_config.py
fixieai/cli/agent/commands.py
fixieai/cli/agent/commands_test.py
fixieai/cli/agent/loader.py
fixieai/cli/agent/tunnel.py
fixieai/cli/auth/__init__.py
fixieai/cli/auth/commands.py
fixieai/cli/auth/oauth_flow.py
fixieai/cli/auth/user_config.py
fixieai/cli/auth/user_config_test.py
fixieai/cli/cli.py
fixieai/cli/session/__init__.py
fixieai/cli/session/commands.py
fixieai/cli/session/console.py
fixieai/cli/utils.py
fixieai/cli/utils_test.py
fixieai/client/__init__.py
fixieai/client/agent.py
fixieai/client/client.py
fixieai/client/client_test.py
fixieai/client/session.py
fixieai/client/utils.py
fixieai/constants.py
fixieai-1.0.4.dist-info/LICENSE
fixieai-1.0.4.dist-info/METADATA
fixieai-1.0.4.dist-info/WHEEL
fixieai-1.0.4.dist-info/entry_points.txt
fixieai-1.0.4.dist-info/RECORD
