Metadata-Version: 2.1
Name: fixieai
Version: 1.0.4
Summary: SDK for the Fixie.ai platform. See: https://fixie.ai
Author: Fixie.ai Team
Author-email: hello@fixie.ai
Requires-Python: >=3.8,<4.0
Classifier: Programming Language :: Python :: 3
Classifier: Programming Language :: Python :: 3.8
Classifier: Programming Language :: Python :: 3.9
Classifier: Programming Language :: Python :: 3.10
Classifier: Programming Language :: Python :: 3.11
Requires-Dist: Deprecated (>=1.2.13,<2.0.0)
Requires-Dist: Pillow
Requires-Dist: PyJWT[crypto] (>=2.6.0,<3.0.0)
Requires-Dist: click (>=8.1.3,<9.0.0)
Requires-Dist: dataclasses-json (>=0.5.7,<0.6.0)
Requires-Dist: fastapi (>=0.89.1,<0.90.0)
Requires-Dist: gql[requests] (>=3.4.1,<4.0.0)
Requires-Dist: oauth2-client (>=1.3.0,<2.0.0)
Requires-Dist: packaging (>=23.0,<24.0)
Requires-Dist: prompt-toolkit
Requires-Dist: pydantic (>=1.10.8)
Requires-Dist: python-dotenv (>=1.0.0,<2.0.0)
Requires-Dist: requests (>=2.28.1,<3.0.0)
Requires-Dist: rich (>=12.6.0,<13.0.0)
Requires-Dist: types-Deprecated (>=1.2.9.2,<2.0.0.0)
Requires-Dist: uvicorn[standard] (>=0.20.0,<0.21.0)
Requires-Dist: validators (>=0.20.0,<0.21.0)
Requires-Dist: watchfiles (>=0.19.0,<0.20.0)
Requires-Dist: wrapt (>=1.15.0,<2.0.0)
